mmmm/Shuvo.py
mmmm/__init__.py
NaimV1-0.2.dist-info/METADATA
NaimV1-0.2.dist-info/WHEEL
NaimV1-0.2.dist-info/top_level.txt
NaimV1-0.2.dist-info/RECORD
